__init__.py
hello.py
svlearn_bootcamp-0.1.7.dist-info/METADATA
svlearn_bootcamp-0.1.7.dist-info/WHEEL
svlearn_bootcamp-0.1.7.dist-info/top_level.txt
svlearn_bootcamp-0.1.7.dist-info/RECORD
